apdt/__init__.py
apdt/config.py
apdt/general.py
apdt/test.py
apdt/alz/__init__.py
apdt/alz/eventdetect.py
apdt/alz/find_sites.py
apdt/alz/graph.py
apdt/alz/prediction_alz.py
apdt/alz/probability.py
apdt/alz/test_alz.py
apdt/alz/utils.py
apdt/io/__init__.py
apdt/io/fake_data.py
apdt/io/loadfoshan.py
apdt/io/loadnms.py
apdt/io/realtime.py
apdt/io/spider.py
apdt/io/test_io.py
apdt/ml/__init__.py
apdt/ml/general.py
apdt/ml/special_dataset.py
apdt/ml/test_ml.py
apdt/ml/tf_model.py
apdt/ml/tf_model2.py
apdt/ml/utils.py
apdt/plt/__init__.py
apdt/plt/logloader.py
apdt/proc/__init__.py
apdt/proc/interpolate.py
apdt/proc/test_proc.py
apdt/proc/utils.py
apdt-0.1.9.dist-info/LICENSE
apdt-0.1.9.dist-info/METADATA
apdt-0.1.9.dist-info/WHEEL
apdt-0.1.9.dist-info/top_level.txt
apdt-0.1.9.dist-info/RECORD
