Metadata-Version: 2.1
Name: apdt
Version: 0.1.9
Summary: apdt
Home-page: https://github.com/Zhiyuan-Wu/apdt
Author: Zhiyuan-Wu
Author-email: 86562713@qq.com
Maintainer: Zhiyuan-Wu
Maintainer-email: 86562713@qq.com
License: Apache License Version 2.0
Platform: UNKNOWN
Classifier: Development Status :: 4 - Beta
Classifier: Programming Language :: Python :: 3.7
Classifier: Programming Language :: Python :: 3.6
Classifier: Operating System :: OS Independent
Requires-Dist: numpy
Requires-Dist: pandas
Requires-Dist: sklearn
